MANIFEST.in
README.md
setup.py
flaskoidc/__init__.py
flaskoidc/auth_client.py
flaskoidc/config.py
flaskoidc/models.py
hey_auth.egg-info/PKG-INFO
hey_auth.egg-info/SOURCES.txt
hey_auth.egg-info/dependency_links.txt
hey_auth.egg-info/requires.txt
hey_auth.egg-info/top_level.txt