Metadata-Version: 2.1
Name: hey-auth
Version: 1.0.3
Summary: Flask wrapper with pre-configured OAuth2 and OIDC support
Home-page: https://github.com/coderbarns/flaskoidc.git
Author: Aarni Alasaarela
Author-email: coderbarns@gmail.com
License: UNKNOWN
Platform: UNKNOWN
Requires-Python: >=3.6
